hat/qt.py
hat_qt-0.5.1.dist-info/LICENSE
hat_qt-0.5.1.dist-info/METADATA
hat_qt-0.5.1.dist-info/WHEEL
hat_qt-0.5.1.dist-info/entry_points.txt
hat_qt-0.5.1.dist-info/top_level.txt
hat_qt-0.5.1.dist-info/RECORD
