Metadata-Version: 2.1
Name: hat-qt
Version: 0.5.1
Summary: Hat Qt utility library
Home-page: https://github.com/hat-open/hat-qt
License: Apache-2.0
Platform: UNKNOWN
Classifier: Programming Language :: Python :: 3
Classifier: License :: OSI Approved :: Apache Software License
Requires-Python: >=3.8
License-File: LICENSE
Requires-Dist: hat-aio (~=0.6.0)
Requires-Dist: hat-util (~=0.5.5)
Requires-Dist: pyside6 (~=6.2.2)
